LICENSE
MANIFEST.in
README.md
requirements.txt
setup.py
tabledbmapper/__init__.py
tabledbmapper/engine.py
tabledbmapper/facade.py
tabledbmapper/logger.py
tabledbmapper/sql_builder.py
tabledbmapper.egg-info/PKG-INFO
tabledbmapper.egg-info/SOURCES.txt
tabledbmapper.egg-info/dependency_links.txt
tabledbmapper.egg-info/not-zip-safe
tabledbmapper.egg-info/requires.txt
tabledbmapper.egg-info/top_level.txt
tabledbmapper/manager/__init__.py
tabledbmapper/manager/manager.py
tabledbmapper/manager/xml_config.py
tabledbmapper/manager/session/__init__.py
tabledbmapper/manager/session/pool.py
tabledbmapper/manager/session/sql_session.py
tabledbmapper/manager/session/sql_session_factory.py
tabledbmapper/manager/session/decorators/__init__.py
tabledbmapper/manager/session/decorators/sql_session.py